aiolyric/__init__.py
aiolyric/client.py
aiolyric/const.py
aiolyric/exceptions.py
aiolyric/objects/__init__.py
aiolyric/objects/base.py
aiolyric/objects/device.py
aiolyric/objects/location.py
aiolyric/objects/priority.py
aiolyric-2.0.2.dist-info/licenses/LICENSE
tests/objects/__init__.py
tests/objects/test_device.py
tests/objects/test_location.py
tests/objects/test_priority.py
aiolyric-2.0.2.dist-info/METADATA
aiolyric-2.0.2.dist-info/WHEEL
aiolyric-2.0.2.dist-info/top_level.txt
aiolyric-2.0.2.dist-info/RECORD
